{
  "units": [
    {
      "symbol": "J",
      "name": "Joule",
      "category": "SI",
      "type": "linear",
      "factor_to_J": 1,
      "dimensions": {"M": 1, "L": 2, "T": -2}
    },
    {
      "symbol": "kJ",
      "name": "Kilojoule",
      "category": "SI",
      "type": "linear",
      "factor_to_J": 1000,
      "dimensions": {"M": 1, "L": 2, "T": -2}
    },
    {
      "symbol": "eV",
      "name": "Electronvolt",
      "category": "atomic",
      "type": "linear",
      "factor_to_J": 1.602176634e-19,
      "dimensions": {"M": 1, "L": 2, "T": -2}
    },
    {
      "symbol": "Eh",
      "name": "Hartree",
      "category": "atomic",
      "type": "linear",
      "factor_to_J": 4.3597e-18,
      "dimensions": {"M": 1, "L": 2, "T": -2}
    },
    {
      "symbol": "cal",
      "name": "Calorie",
      "category": "thermochemical",
      "type": "linear",
      "factor_to_J": 4.184,
      "dimensions": {"M": 1, "L": 2, "T": -2}
    },
    {
      "symbol": "kcal",
      "name": "Kilocalorie",
      "category": "thermochemical",
      "type": "linear",
      "factor_to_J": 4184,
      "dimensions": {"M": 1, "L": 2, "T": -2}
    },
    {
      "symbol": "kJ/mol",
      "name": "kJ per mole",
      "category": "molar",
      "type": "linear",
      "factor_to_J": 1.6605e-21,
      "dimensions": {"M": 1, "L": 2, "T": -2, "N": -1}
    },
    {
      "symbol": "kcal/mol",
      "name": "kcal per mole",
      "category": "molar",
      "type": "linear",
      "factor_to_J": 6.9477e-21,
      "dimensions": {"M": 1, "L": 2, "T": -2, "N": -1}
    },
    {
      "symbol": "K",
      "name": "Kelvin",
      "category": "thermal",
      "type": "linear",
      "factor_to_J": 1.380649e-23,
      "dimensions": {"M": 1, "L": 2, "T": -2}
    },
    {
      "symbol": "cm-1",
      "name": "Wavenumber (cm\u207b\u00b9)",
      "category": "spectroscopic",
      "type": "wavenumber",
      "scale_to_per_metre": 100,
      "dimensions": {"L": -1}
    },
    {
      "symbol": "Hz",
      "name": "Hertz",
      "category": "spectroscopic",
      "type": "photon_frequency",
      "scale_to_Hz": 1,
      "dimensions": {"T": -1}
    },
    {
      "symbol": "nm",
      "name": "Nanometre",
      "category": "spectroscopic",
      "type": "photon_wavelength",
      "scale_to_metres": 1e-9,
      "dimensions": {"L": 1}
    }
  ],
  "energy_levels": {
    "low_threshold_J": 1e-23,
    "high_threshold_J": 1e-17,
    "labels": {
      "low": "Low (thermal)",
      "medium": "Medium",
      "high": "High (ionising)"
    }
  },
  "em_regions": [
    {
      "name": "Radio",
      "max_energy_J": 1.99e-28,
      "wavelength_range": "> 1 mm",
      "molecular_process": "Nuclear spin flips (NMR)"
    },
    {
      "name": "Microwave",
      "max_energy_J": 1.99e-22,
      "wavelength_range": "1 mm - 1 m",
      "molecular_process": "Molecular rotational transitions"
    },
    {
      "name": "Infrared",
      "max_energy_J": 2.55e-19,
      "wavelength_range": "780 nm - 1 mm",
      "molecular_process": "Molecular vibrational modes"
    },
    {
      "name": "Visible",
      "max_energy_J": 5.23e-19,
      "wavelength_range": "380 - 780 nm",
      "molecular_process": "Outer-electron excitation"
    },
    {
      "name": "UV",
      "max_energy_J": 1.99e-17,
      "wavelength_range": "10 - 380 nm",
      "molecular_process": "Valence electron excitation"
    },
    {
      "name": "X-ray",
      "max_energy_J": 1.99e-14,
      "wavelength_range": "0.01 - 10 nm",
      "molecular_process": "Core-electron excitation / ionisation"
    },
    {
      "name": "Gamma",
      "max_energy_J": 1e99,
      "wavelength_range": "< 0.01 nm",
      "molecular_process": "Nuclear transitions / pair production"
    }
  ]
}
